Metadata-Version: 1.0
Name: jnowicki99-probability
Version: 0.1
Summary: Gaussian and Binomial distributions
Home-page: UNKNOWN
Author: Jakub Nowicki
Author-email: j99nowicki@gmail.com
License: UNKNOWN
Platform: UNKNOWN
